jaqpot_api_client/__about__.py
jaqpot_api_client/__init__.py
jaqpot_api_client/api_client.py
jaqpot_api_client/api_response.py
jaqpot_api_client/configuration.py
jaqpot_api_client/exceptions.py
jaqpot_api_client/py.typed
jaqpot_api_client/rest.py
jaqpot_api_client/api/__init__.py
jaqpot_api_client/api/admin_api.py
jaqpot_api_client/api/api_keys_api.py
jaqpot_api_client/api/auth_api.py
jaqpot_api_client/api/dataset_api.py
jaqpot_api_client/api/feature_api.py
jaqpot_api_client/api/large_model_api.py
jaqpot_api_client/api/lead_api.py
jaqpot_api_client/api/model_api.py
jaqpot_api_client/api/model_download_api.py
jaqpot_api_client/api/organization_api.py
jaqpot_api_client/api/organization_invitation_api.py
jaqpot_api_client/api/user_api.py
jaqpot_api_client/api/user_settings0_api.py
jaqpot_api_client/api/user_settings_api.py
jaqpot_api_client/models/__init__.py
jaqpot_api_client/models/api_key.py
jaqpot_api_client/models/archive_model200_response.py
jaqpot_api_client/models/binary_classification_scores.py
jaqpot_api_client/models/bounding_box_doa.py
jaqpot_api_client/models/city_block_doa.py
jaqpot_api_client/models/create_api_key201_response.py
jaqpot_api_client/models/create_invitations_request.py
jaqpot_api_client/models/create_large_model201_response.py
jaqpot_api_client/models/dataset.py
jaqpot_api_client/models/dataset_csv.py
jaqpot_api_client/models/dataset_result_type.py
jaqpot_api_client/models/dataset_type.py
jaqpot_api_client/models/doa.py
jaqpot_api_client/models/doa_method.py
jaqpot_api_client/models/docker_config.py
jaqpot_api_client/models/error_code.py
jaqpot_api_client/models/error_response.py
jaqpot_api_client/models/feature.py
jaqpot_api_client/models/feature_possible_value.py
jaqpot_api_client/models/feature_type.py
jaqpot_api_client/models/get_all_api_keys_for_user200_response_inner.py
jaqpot_api_client/models/get_all_models200_response.py
jaqpot_api_client/models/get_datasets200_response.py
jaqpot_api_client-7.0.3.dist-info/METADATA
jaqpot_api_client-7.0.3.dist-info/WHEEL
jaqpot_api_client-7.0.3.dist-info/licenses/LICENSE.txt
jaqpot_api_client-7.0.3.dist-info/RECORD
