Metadata-Version: 2.4
Name: jaqpot-api-client
Version: 7.0.3
Summary: A python client for the Jaqpot API generated from the OpenAPI specification
Project-URL: Documentation, https://github.com/ntua-unit-of-control-and-informatics/jaqpot-api-client-python#readme
Project-URL: Issues, https://github.com/ntua-unit-of-control-and-informatics/jaqpot-api-client-python/issues
Project-URL: Source, https://github.com/ntua-unit-of-control-and-informatics/jaqpot-api-client-python
Author-email: UPCI NTUA <upci.ntua@gmail.com>
License-Expression: MIT
License-File: LICENSE.txt
Classifier: Development Status :: 4 - Beta
Classifier: Programming Language :: Python
Classifier: Programming Language :: Python :: 3.8
Classifier: Programming Language :: Python :: 3.9
Classifier: Programming Language :: Python :: 3.10
Classifier: Programming Language :: Python :: 3.11
Classifier: Programming Language :: Python :: 3.12
Classifier: Programming Language :: Python :: Implementation :: CPython
Classifier: Programming Language :: Python :: Implementation :: PyPy
Requires-Python: >=3.8
